Workbook

Sheet По разделам
A1: Раздел | B1: Оборот, ₸ | C1: Доля | D1: Заказы, шт | E1: Ниш | F1: Средний чек, ₸
A2: Телефоны и гаджеты | B2: =SUMIFS('Все ниши'!$E$2:$E$2267,'Все ниши'!$C$2:$C$2267,A2) | C2: =B2/SUM($B$2:$B$20) | D2: =SUMIFS('Все ниши'!$F$2:$F$2267,'Все ниши'!$C$2:$C$2267,A2) | E2: =COUNTIF('Все ниши'!$C$2:$C$2267,A2) | F2: =IFERROR(B2/D2,0)
A3: Бытовая техника | B3: =SUMIFS('Все ниши'!$E$2:$E$2267,'Все ниши'!$C$2:$C$2267,A3) | C3: =B3/SUM($B$2:$B$20) | D3: =SUMIFS('Все ниши'!$F$2:$F$2267,'Все ниши'!$C$2:$C$2267,A3) | E3: =COUNTIF('Все ниши'!$C$2:$C$2267,A3) | F3: =IFERROR(B3/D3,0)
A4: Мебель | B4: =SUMIFS('Все ниши'!$E$2:$E$2267,'Все ниши'!$C$2:$C$2267,A4) | C4: =B4/SUM($B$2:$B$20) | D4: =SUMIFS('Все ниши'!$F$2:$F$2267,'Все ниши'!$C$2:$C$2267,A4) | E4: =COUNTIF('Все ниши'!$C$2:$C$2267,A4) | F4: =IFERROR(B4/D4,0)
A5: Красота и здоровье | B5: =SUMIFS('Все ниши'!$E$2:$E$2267,'Все ниши'!$C$2:$C$2267,A5) | C5: =B5/SUM($B$2:$B$20) | D5: =SUMIFS('Все ниши'!$F$2:$F$2267,'Все ниши'!$C$2:$C$2267,A5) | E5: =COUNTIF('Все ниши'!$C$2:$C$2267,A5) | F5: =IFERROR(B5/D5,0)
A6: Товары для дома и дачи | B6: =SUMIFS('Все ниши'!$E$2:$E$2267,'Все ниши'!$C$2:$C$2267,A6) | C6: =B6/SUM($B$2:$B$20) | D6: =SUMIFS('Все ниши'!$F$2:$F$2267,'Все ниши'!$C$2:$C$2267,A6) | E6: =COUNTIF('Все ниши'!$C$2:$C$2267,A6) | F6: =IFERROR(B6/D6,0)
A7: Компьютеры | B7: =SUMIFS('Все ниши'!$E$2:$E$2267,'Все ниши'!$C$2:$C$2267,A7) | C7: =B7/SUM($B$2:$B$20) | D7: =SUMIFS('Все ниши'!$F$2:$F$2267,'Все ниши'!$C$2:$C$2267,A7) | E7: =COUNTIF('Все ниши'!$C$2:$C$2267,A7) | F7: =IFERROR(B7/D7,0)
A8: Автотовары | B8: =SUMIFS('Все ниши'!$E$2:$E$2267,'Все ниши'!$C$2:$C$2267,A8) | C8: =B8/SUM($B$2:$B$20) | D8: =SUMIFS('Все ниши'!$F$2:$F$2267,'Все ниши'!$C$2:$C$2267,A8) | E8: =COUNTIF('Все ниши'!$C$2:$C$2267,A8) | F8: =IFERROR(B8/D8,0)
A9: Аптека | B9: =SUMIFS('Все ниши'!$E$2:$E$2267,'Все ниши'!$C$2:$C$2267,A9) | C9: =B9/SUM($B$2:$B$20) | D9: =SUMIFS('Все ниши'!$F$2:$F$2267,'Все ниши'!$C$2:$C$2267,A9) | E9: =COUNTIF('Все ниши'!$C$2:$C$2267,A9) | F9: =IFERROR(B9/D9,0)
A10: ТВ, Аудио, Видео | B10: =SUMIFS('Все ниши'!$E$2:$E$2267,'Все ниши'!$C$2:$C$2267,A10) | C10: =B10/SUM($B$2:$B$20) | D10: =SUMIFS('Все ниши'!$F$2:$F$2267,'Все ниши'!$C$2:$C$2267,A10) | E10: =COUNTIF('Все ниши'!$C$2:$C$2267,A10) | F10: =IFERROR(B10/D10,0)
A11: Строительство, ремонт | B11: =SUMIFS('Все ниши'!$E$2:$E$2267,'Все ниши'!$C$2:$C$2267,A11) | C11: =B11/SUM($B$2:$B$20) | D11: =SUMIFS('Все ниши'!$F$2:$F$2267,'Все ниши'!$C$2:$C$2267,A11) | E11: =COUNTIF('Все ниши'!$C$2:$C$2267,A11) | F11: =IFERROR(B11/D11,0)
A12: Спорт, туризм | B12: =SUMIFS('Все ниши'!$E$2:$E$2267,'Все ниши'!$C$2:$C$2267,A12) | C12: =B12/SUM($B$2:$B$20) | D12: =SUMIFS('Все ниши'!$F$2:$F$2267,'Все ниши'!$C$2:$C$2267,A12) | E12: =COUNTIF('Все ниши'!$C$2:$C$2267,A12) | F12: =IFERROR(B12/D12,0)
A13: Украшения | B13: =SUMIFS('Все ниши'!$E$2:$E$2267,'Все ниши'!$C$2:$C$2267,A13) | C13: =B13/SUM($B$2:$B$20) | D13: =SUMIFS('Все ниши'!$F$2:$F$2267,'Все ниши'!$C$2:$C$2267,A13) | E13: =COUNTIF('Все ниши'!$C$2:$C$2267,A13) | F13: =IFERROR(B13/D13,0)
... A20: Канцелярские товары | B20: =SUMIFS('Все ниши'!$E$2:$E$2267,'Все ниши'!$C$2:$C$2267,A20) | C20: =B20/SUM($B$2:$B$20) | D20: =SUMIFS('Все ниши'!$F$2:$F$2267,'Все ниши'!$C$2:$C$2267,A20) | E20: =COUNTIF('Все ниши'!$C$2:$C$2267,A20) | F20: =IFERROR(B20/D20,0)
A21: ИТОГО | B21: =SUM(B2:B20) | C21: =SUM(C2:C20) | D21: =SUM(D2:D20) | E21: =SUM(E2:E20) | F21: =IFERROR(B21/D21,0)
A23: Источник: RedStat (аналитика Kaspi.kz), период — август 2026 (календарный месяц), метрика — выручка (sale_amount). Все суммы в тенге.

Sheet Все ниши
A1: № | B1: Ниша | C1: Раздел | D1: Путь в каталоге | E1: Оборот, ₸ | F1: Заказы, шт | G1: Средний чек, ₸ | H1: SKU, шт | I1: Брендов | J1: Выручка на SKU, ₸ | K1: Доля рынка | L1: Накопл. доля | M1: ID ниши | N1: RedStat | O1: Kaspi
A2: 1 | B2: Смартфоны | C2: Телефоны и гаджеты | D2: Телефоны и гаджеты → Смартфоны | E2: 40740351810 | F2: 110088 | G2: =IFERROR(E2/F2,0) | H2: 3302 | I2: 36 | J2: =IFERROR(E2/H2,0) | K2: =E2/'По разделам'!$B$21 | L2: =K2 | M2: 00003 | N2: https://app.redstat.kz/niche/00003?event_date=2026-08-01 | O2: https://kaspi.kz/shop/c/smartphones/
A3: 2 | B3: Витамины и БАД | C3: Аптека | D3: Аптека → Витамины и БАД | E3: 9516905073 | F3: 1381320 | G3: =IFERROR(E3/F3,0) | H3: 18879 | I3: 1795 | J3: =IFERROR(E3/H3,0) | K3: =E3/'По разделам'!$B$21 | L3: =L2+K3 | M3: 04550 | N3: https://app.redstat.kz/niche/04550?event_date=2026-08-01 | O3: https://kaspi.kz/shop/c/vitamins/
A4: 3 | B4: Ноутбуки | C4: Компьютеры | D4: Компьютеры → Ноутбуки и аксессуары → Ноутбуки | E4: 5965719185 | F4: 16459 | G4: =IFERROR(E4/F4,0) | H4: 1811 | I4: 78 | J4: =IFERROR(E4/H4,0) | K4: =E4/'По разделам'!$B$21 | L4: =L3+K4 | M4: 00588 | N4: https://app.redstat.kz/niche/00588?event_date=2026-08-01 | O4: https://kaspi.kz/shop/c/notebooks/
A5: 4 | B5: Холодильники | C5: Бытовая техника | D5: Бытовая техника → Крупная техника для дома → Холодильники | E5: 3728770671 | F5: 17448 | G5: =IFERROR(E5/F5,0) | H5: 1187 | I5: 88 | J5: =IFERROR(E5/H5,0) | K5: =E5/'По разделам'!$B$21 | L5: =L4+K5 | M5: 00025 | N5: https://app.redstat.kz/niche/00025?event_date=2026-08-01 | O5: https://kaspi.kz/shop/c/refrigerators/
A6: 5 | B6: Стиральные машины | C6: Бытовая техника | D6: Бытовая техника → Крупная техника для дома → Стиральные машины | E6: 3472279970 | F6: 20601 | G6: =IFERROR(E6/F6,0) | H6: 939 | I6: 99 | J6: =IFERROR(E6/H6,0) | K6: =E6/'По разделам'!$B$21 | L6: =L5+K6 | M6: 00035 | N6: https://app.redstat.kz/niche/00035?event_date=2026-08-01 | O6: https://kaspi.kz/shop/c/washers/
A7: 6 | B7: Шины для легковых и внедорожных автомобилей | C7: Автотовары | D7: Автотовары → Шины → Шины для легковых и внедорожных автомобилей | E7: 3323820614 | F7: 28278 | G7: =IFERROR(E7/F7,0) | H7: 8227 | I7: 209 | J7: =IFERROR(E7/H7,0) | K7: =E7/'По разделам'!$B$21 | L7: =L6+K7 | M7: 02640 | N7: https://app.redstat.kz/niche/02640?event_date=2026-08-01 | O7: https://kaspi.kz/shop/c/passenger%20car%20tires/
A8: 7 | B8: Пылесосы | C8: Бытовая техника | D8: Бытовая техника → Малая техника для дома → Пылесосы | E8: 2473506910 | F8: 98084 | G8: =IFERROR(E8/F8,0) | H8: 1937 | I8: 429 | J8: =IFERROR(E8/H8,0) | K8: =E8/'По разделам'!$B$21 | L8: =L7+K8 | M8: 00036 | N8: https://app.redstat.kz/niche/00036?event_date=2026-08-01 | O8: https://kaspi.kz/shop/c/vacuum%20cleaners/
A9: 8 | B9: Телевизоры | C9: ТВ, Аудио, Видео | D9: ТВ, Аудио, Видео → Телевизоры | E9: 2343539408 | F9: 12873 | G9: =IFERROR(E9/F9,0) | H9: 900 | I9: 91 | J9: =IFERROR(E9/H9,0) | K9: =E9/'По разделам'!$B$21 | L9: =L8+K9 | M9: 05374 | N9: https://app.redstat.kz/niche/05374?event_date=2026-08-01 | O9: https://kaspi.kz/shop/c/tvs/
A10: 9 | B10: Диваны и комплекты мягкой мебели | C10: Мебель | D10: Мебель → Гостиная → Диваны и комплекты мягкой мебели | E10: 2287100456 | F10: 18456 | G10: =IFERROR(E10/F10,0) | H10: 2718 | I10: 268 | J10: =IFERROR(E10/H10,0) | K10: =E10/'По разделам'!$B$21 | L10: =L9+K10 | M10: 00562 | N10: https://app.redstat.kz/niche/00562?event_date=2026-08-01 | O10: https://kaspi.kz/shop/c/sofas/
A11: 10 | B11: Планшеты | C11: Компьютеры | D11: Компьютеры → Планшеты и аксессуары → Планшеты | E11: 2036218563 | F11: 12214 | G11: =IFERROR(E11/F11,0) | H11: 844 | I11: 92 | J11: =IFERROR(E11/H11,0) | K11: =E11/'По разделам'!$B$21 | L11: =L10+K11 | M11: 01325 | N11: https://app.redstat.kz/niche/01325?event_date=2026-08-01 | O11: https://kaspi.kz/shop/c/tablets/
A12: 11 | B12: Шкафы для одежды | C12: Мебель | D12: Мебель → Спальня → Шкафы для одежды | E12: 1981417411 | F12: 19254 | G12: =IFERROR(E12/F12,0) | H12: 2694 | I12: 243 | J12: =IFERROR(E12/H12,0) | K12: =E12/'По разделам'!$B$21 | L12: =L11+K12 | M12: 00316 | N12: https://app.redstat.kz/niche/00316?event_date=2026-08-01 | O12: https://kaspi.kz/shop/c/wardrobes/
A13: 12 | B13: Морозильники | C13: Бытовая техника | D13: Бытовая техника → Крупная техника для дома → Морозильники | E13: 1815575249 | F13: 13648 | G13: =IFERROR(E13/F13,0) | H13: 652 | I13: 81 | J13: =IFERROR(E13/H13,0) | K13: =E13/'По разделам'!$B$21 | L13: =L12+K13 | M13: 00026 | N13: https://app.redstat.kz/niche/00026?event_date=2026-08-01 | O13: https://kaspi.kz/shop/c/freezers/
A14: 13 | B14: Кондиционеры | C14: Бытовая техника | D14: Бытовая техника → Климатическая техника → Кондиционеры | E14: 1794465081 | F14: 9994 | G14: =IFERROR(E14/F14,0) | H14: 848 | I14: 99 | J14: =IFERROR(E14/H14,0) | K14: =E14/'По разделам'!$B$21 | L14: =L13+K14 | M14: 00047 | N14: https://app.redstat.kz/niche/00047?event_date=2026-08-01 | O14: https://kaspi.kz/shop/c/air%20conditioners/
... A19: 18 | B19: Парфюмерия | C19: Красота и здоровье | D19: Красота и здоровье → Парфюмерия | E19: 1359807981 | F19: 122812 | G19: =IFERROR(E19/F19,0) | H19: 11822 | I19: 755 | J19: =IFERROR(E19/H19,0) | K19: =E19/'По разделам'!$B$21 | L19: =L18+K19 | M19: 00563 | N19: https://app.redstat.kz/niche/00563?event_date=2026-08-01 | O19: https://kaspi.kz/shop/c/perfumes/
A20: 19 | B20: Печи и грили | C20: Бытовая техника | D20: Бытовая техника → Мелкая техника для кухни → Печи и грили → Печи и грили | E20: 1287669658 | F20: 44994 | G20: =IFERROR(E20/F20,0) | H20: 1774 | I20: 369 | J20: =IFERROR(E20/H20,0) | K20: =E20/'По разделам'!$B$21 | L20: =L19+K20 | M20: q86fab4ff138e681 | N20: https://app.redstat.kz/niche/q86fab4ff138e681?event_date=2026-08-01
A21: 20 | B21: Системные блоки | C21: Компьютеры | D21: Компьютеры → Настольные компьютеры → Системные блоки | E21: 1098686317 | F21: 2136 | G21: =IFERROR(E21/F21,0) | H21: 600 | I21: 96 | J21: =IFERROR(E21/H21,0) | K21: =E21/'По разделам'!$B$21 | L21: =L20+K21 | M21: 05403 | N21: https://app.redstat.kz/niche/05403?event_date=2026-08-01 | O21: https://kaspi.kz/shop/c/desktops/
A22: 21 | B22: Садовая техника | C22: Товары для дома и дачи | D22: Товары для дома и дачи → Дача, сад и огород → Садовая техника → Садовая техника | E22: 1028872096 | F22: 23419 | G22: =IFERROR(E22/F22,0) | H22: 3893 | I22: 448 | J22: =IFERROR(E22/H22,0) | K22: =E22/'По разделам'!$B$21 | L22: =L21+K22 | M22: qb71a7a07068894e | N22: https://app.redstat.kz/niche/qb71a7a07068894e?event_date=2026-08-01
A23: 22 | B23: Кольца ювелирные | C23: Украшения | D23: Украшения → Кольца → Кольца ювелирные | E23: 1013930477 | F23: 23440 | G23: =IFERROR(E23/F23,0) | H23: 6629 | I23: 497 | J23: =IFERROR(E23/H23,0) | K23: =E23/'По разделам'!$B$21 | L23: =L22+K23 | M23: 00743 | N23: https://app.redstat.kz/niche/00743?event_date=2026-08-01 | O23: https://kaspi.kz/shop/c/rings/
A24: 23 | B24: Комплекты ювелирных украшений | C24: Украшения | D24: Украшения → Комплекты украшений → Комплекты ювелирных украшений | E24: 994048454 | F24: 10855 | G24: =IFERROR(E24/F24,0) | H24: 1838 | I24: 361 | J24: =IFERROR(E24/H24,0) | K24: =E24/'По разделам'!$B$21 | L24: =L23+K24 | M24: 01246 | N24: https://app.redstat.kz/niche/01246?event_date=2026-08-01 | O24: https://kaspi.kz/shop/c/jewelry%20sets/
A25: 24 | B25: Посуда для приготовления | C25: Товары для дома и дачи | D25: Товары для дома и дачи → Посуда и принадлежности → Посуда для приготовления → Посуда для приготовления | E25: 974719576 | F25: 88120 | G25: =IFERROR(E25/F25,0) | H25: 8566 | I25: 653 | J25: =IFERROR(E25/H25,0) | K25: =E25/'По разделам'!$B$21 | L25: =L24+K25 | M25: qd8920d58c7de0d8 | N25: https://app.redstat.kz/niche/qd8920d58c7de0d8?event_date=2026-08-01
A26: 25 | B26: Матрасы | C26: Мебель | D26: Мебель → Спальня → Матрасы | E26: 955552735 | F26: 18113 | G26: =IFERROR(E26/F26,0) | H26: 3302 | I26: 221 | J26: =IFERROR(E26/H26,0) | K26: =E26/'По разделам'!$B$21 | L26: =L25+K26 | M26: 00317 | N26: https://app.redstat.kz/niche/00317?event_date=2026-08-01 | O26: https://kaspi.kz/shop/c/bedroom%20mattresses/
A27: 26 | B27: Серьги ювелирные | C27: Украшения | D27: Украшения → Серьги → Серьги ювелирные | E27: 954633475 | F27: 25069 | G27: =IFERROR(E27/F27,0) | H27: 5310 | I27: 481 | J27: =IFERROR(E27/H27,0) | K27: =E27/'По разделам'!$B$21 | L27: =L26+K27 | M27: 00744 | N27: https://app.redstat.kz/niche/00744?event_date=2026-08-01 | O27: https://kaspi.kz/shop/c/earrings/
A28: 27 | B28: Шины для грузового транспорта и спецтехники | C28: Автотовары | D28: Автотовары → Шины → Шины для грузового транспорта и спецтехники | E28: 952049889 | F28: 2729 | G28: =IFERROR(E28/F28,0) | H28: 887 | I28: 110 | J28: =IFERROR(E28/H28,0) | K28: =E28/'По разделам'!$B$21 | L28: =L27+K28 | M28: 02634 | N28: https://app.redstat.kz/niche/02634?event_date=2026-08-01 | O28: https://kaspi.kz/shop/c/heavy%20duty%20tires/
A29: 28 | B29: Прочая кухонная техника | C29: Бытовая техника | D29: Бытовая техника → Мелкая техника для кухни → Прочая кухонная техника → Прочая кухонная техника | E29: 917853483 | F29: 31743 | G29: =IFERROR(E29/F29,0) | H29: 1952 | I29: 476 | J29: =IFERROR(E29/H29,0) | K29: =E29/'По разделам'!$B$21 | L29: =L28+K29 | M29: qd9b3ff4ab6368a3 | N29: https://app.redstat.kz/niche/qd9b3ff4ab6368a3?event_date=2026-08-01
A30: 29 | B30: Цепи ювелирные | C30: Украшения | D30: Украшения → Цепи → Цепи ювелирные | E30: 887209104 | F30: 13442 | G30: =IFERROR(E30/F30,0) | H30: 1979 | I30: 285 | J30: =IFERROR(E30/H30,0) | K30: =E30/'По разделам'!$B$21 | L30: =L29+K30 | M30: 01753 | N30: https://app.redstat.kz/niche/01753?event_date=2026-08-01 | O30: https://kaspi.kz/shop/c/necklaces/
A31: 30 | B31: Отопительные котлы | C31: Бытовая техника | D31: Бытовая техника → Отопительные котлы | E31: 850050389 | F31: 3103 | G31: =IFERROR(E31/F31,0) | H31: 748 | I31: 121 | J31: =IFERROR(E31/H31,0) | K31: =E31/'По разделам'!$B$21 | L31: =L30+K31 | M31: 00103 | N31: https://app.redstat.kz/niche/00103?event_date=2026-08-01 | O31: https://kaspi.kz/shop/c/boilers/
A32: 31 | B32: Обеденные группы | C32: Мебель | D32: Мебель → Кухня → Обеденные группы | E32: 832802690 | F32: 7545 | G32: =IFERROR(E32/F32,0) | H32: 879 | I32: 106 | J32: =IFERROR(E32/H32,0) | K32: =E32/'По разделам'!$B$21 | L32: =L31+K32 | M32: 05356 | N32: https://app.redstat.kz/niche/05356?event_date=2026-08-01 | O32: https://kaspi.kz/shop/c/dining%20sets/
A33: 32 | B33: Принтеры и МФУ | C33: Компьютеры | D33: Компьютеры → Оргтехника и расходные материалы → Принтеры и МФУ | E33: 822123414 | F33: 8129 | G33: =IFERROR(E33/F33,0) | H33: 259 | I33: 14 | J33: =IFERROR(E33/H33,0) | K33: =E33/'По разделам'!$B$21 | L33: =L32+K33 | M33: 02930 | N33: https://app.redstat.kz/niche/02930?event_date=2026-08-01 | O33: https://kaspi.kz/shop/c/mf%20printers/
A34: 33 | B34: Уход и гигиена малыша | C34: Детские товары | D34: Детские товары → Для малыша и мамы → Уход и гигиена малыша → Уход и гигиена малыша | E34: 800773333 | F34: 146334 | G34: =IFERROR(E34/F34,0) | H34: 4254 | I34: 549 | J34: =IFERROR(E34/H34,0) | K34: =E34/'По разделам'!$B$21 | L34: =L33+K34 | M34: qcd099c503c60396 | N34: https://app.redstat.kz/niche/qcd099c503c60396?event_date=2026-08-01
A35: 34 | B35: Кухонные комбайны и мясорубки | C35: Бытовая техника | D35: Бытовая техника → Мелкая техника для кухни → Кухонные комбайны и мясорубки → Кухонные комбайны и мясорубки | E35: 798796434 | F35: 14868 | G35: =IFERROR(E35/F35,0) | H35: 742 | I35: 256 | J35: =IFERROR(E35/H35,0) | K35: =E35/'По разделам'!$B$21 | L35: =L34+K35 | M35: qd834b46d8028604 | N35: https://app.redstat.kz/niche/qd834b46d8028604?event_date=2026-08-01
A36: 35 | B36: Духовые шкафы | C36: Бытовая техника | D36: Бытовая техника → Крупная техника для дома → Духовые шкафы | E36: 781589566 | F36: 4242 | G36: =IFERROR(E36/F36,0) | H36: 578 | I36: 59 | J36: =IFERROR(E36/H36,0) | K36: =E36/'По разделам'!$B$21 | L36: =L35+K36 | M36: 00023 | N36: https://app.redstat.kz/niche/00023?event_date=2026-08-01 | O36: https://kaspi.kz/shop/c/ovens/
A37: 36 | B37: Компьютерные и письменные столы | C37: Мебель | D37: Мебель → Офис и кабинет → Компьютерные и письменные столы | E37: 768924023 | F37: 23078 | G37: =IFERROR(E37/F37,0) | H37: 1446 | I37: 208 | J37: =IFERROR(E37/H37,0) | K37: =E37/'По разделам'!$B$21 | L37: =L36+K37 | M37: 05353 | N37: https://app.redstat.kz/niche/05353?event_date=2026-08-01 | O37: https://kaspi.kz/shop/c/computer%20desks/
A38: 37 | B38: Наборы косметики | C38: Красота и здоровье | D38: Красота и здоровье → Наборы косметики | E38: 733174940 | F38: 72382 | G38: =IFERROR(E38/F38,0) | H38: 3742 | I38: 602 | J38: =IFERROR(E38/H38,0) | K38: =E38/'По разделам'!$B$21 | L38: =L37+K38 | M38: 07146 | N38: https://app.redstat.kz/niche/07146?event_date=2026-08-01 | O38: https://kaspi.kz/shop/c/cosmetics%20sets/
A39: 38 | B39: Сумки | C39: Аксессуары | D39: Аксессуары → Сумки, чемоданы, кошельки → Сумки | E39: 725232276 | F39: 158611 | G39: =IFERROR(E39/F39,0) | H39: 8285 | I39: 817 | J39: =IFERROR(E39/H39,0) | K39: =E39/'По разделам'!$B$21 | L39: =L38+K39 | M39: 01770 | N39: https://app.redstat.kz/niche/01770?event_date=2026-08-01 | O39: https://kaspi.kz/shop/c/fashion%20handbags/
A40: 39 | B40: Столовая посуда | C40: Товары для дома и дачи | D40: Товары для дома и дачи → Посуда и принадлежности → Столовая посуда → Столовая посуда | E40: 707606915 | F40: 64517 | G40: =IFERROR(E40/F40,0) | H40: 9768 | I40: 736 | J40: =IFERROR(E40/H40,0) | K40: =E40/'По разделам'!$B$21 | L40: =L39+K40 | M40: q374f64c9f962207 | N40: https://app.redstat.kz/niche/q374f64c9f962207?event_date=2026-08-01
A41: 40 | B41: Электроинструменты | C41: Строительство, ремонт | D41: Строительство, ремонт → Инструменты → Электроинструменты → Электроинструменты | E41: 684444805 | F41: 23319 | G41: =IFERROR(E41/F41,0) | H41: 3050 | I41: 376 | J41: =IFERROR(E41/H41,0) | K41: =E41/'По разделам'!$B$21 | L41: =L40+K41 | M41: q42b272690abdb84 | N41: https://app.redstat.kz/niche/q42b272690abdb84?event_date=2026-08-01
A42: 41 | B42: Водонагреватели | C42: Бытовая техника | D42: Бытовая техника → Климатическая техника → Водонагреватели | E42: 682517851 | F42: 11629 | G42: =IFERROR(E42/F42,0) | H42: 844 | I42: 102 | J42: =IFERROR(E42/H42,0) | K42: =E42/'По разделам'!$B$21 | L42: =L41+K42 | M42: 00040 | N42: https://app.redstat.kz/niche/00040?event_date=2026-08-01 | O42: https://kaspi.kz/shop/c/water%20heaters/
A43: 42 | B43: Кухонные гарнитуры | C43: Мебель | D43: Мебель → Кухня → Кухонные гарнитуры | E43: 680827067 | F43: 4353 | G43: =IFERROR(E43/F43,0) | H43: 716 | I43: 94 | J43: =IFERROR(E43/H43,0) | K43: =E43/'По разделам'!$B$21 | L43: =L42+K43 | M43: 00772 | N43: https://app.redstat.kz/niche/00772?event_date=2026-08-01 | O43: https://kaspi.kz/shop/c/kitchen%20sets/
A44: 43 | B44: Фены | C44: Красота и здоровье | D44: Красота и здоровье → Техника и оборудование для красоты → Фены | E44: 672219305 | F44: 31097 | G44: =IFERROR(E44/F44,0) | H44: 1734 | I44: 410 | J44: =IFERROR(E44/H44,0) | K44: =E44/'По разделам'!$B$21 | L44: =L43+K44 | M44: 06220 | N44: https://app.redstat.kz/niche/06220?event_date=2026-08-01 | O44: https://kaspi.kz/shop/c/hair%20dryers/
A45: 44 | B45: Браслеты ювелирные | C45: Украшения | D45: Украшения → Браслеты → Браслеты ювелирные | E45: 670303778 | F45: 14878 | G45: =IFERROR(E45/F45,0) | H45: 2532 | I45: 399 | J45: =IFERROR(E45/H45,0) | K45: =E45/'По разделам'!$B$21 | L45: =L44+K45 | M45: 00746 | N45: https://app.redstat.kz/niche/00746?event_date=2026-08-01 | O45: https://kaspi.kz/shop/c/bracelets/
A46: 45 | B46: Учебники и пособия | C46: Досуг, книги | D46: Досуг, книги → Книги → Учебники и пособия | E46: 663600678 | F46: 215503 | G46: =IFERROR(E46/F46,0) | H46: 5636 | I46: 218 | J46: =IFERROR(E46/H46,0) | K46: =E46/'По разделам'!$B$21 | L46: =L45+K46 | M46: 00931 | N46: https://app.redstat.kz/niche/00931?event_date=2026-08-01 | O46: https://kaspi.kz/shop/c/schoolbooks%20and%20study%20guides/
A47: 46 | B47: Игровые приставки | C47: ТВ, Аудио, Видео | D47: ТВ, Аудио, Видео → Развлечения → Игровые приставки | E47: 663160328 | F47: 4439 | G47: =IFERROR(E47/F47,0) | H47: 262 | I47: 35 | J47: =IFERROR(E47/H47,0) | K47: =E47/'По разделам'!$B$21 | L47: =L46+K47 | M47: 00156 | N47: https://app.redstat.kz/niche/00156?event_date=2026-08-01 | O47: https://kaspi.kz/shop/c/game%20consoles/
A48: 47 | B48: Тональные средства | C48: Красота и здоровье | D48: Красота и здоровье → Декоративная косметика → Тональные средства | E48: 642694202 | F48: 123665 | G48: =IFERROR(E48/F48,0) | H48: 2909 | I48: 343 | J48: =IFERROR(E48/H48,0) | K48: =E48/'По разделам'!$B$21 | L48: =L47+K48 | M48: 04995 | N48: https://app.redstat.kz/niche/04995?event_date=2026-08-01 | O48: https://kaspi.kz/shop/c/foundation/
A49: 48 | B49: Стулья | C49: Мебель | D49: Мебель → Кухня → Стулья | E49: 641684356 | F49: 19867 | G49: =IFERROR(E49/F49,0) | H49: 2005 | I49: 234 | J49: =IFERROR(E49/H49,0) | K49: =E49/'По разделам'!$B$21 | L49: =L48+K49 | M49: 05342 | N49: https://app.redstat.kz/niche/05342?event_date=2026-08-01 | O49: https://kaspi.kz/shop/c/kitchen%20chairs/
A50: 49 | B50: Посудомоечные машины | C50: Бытовая техника | D50: Бытовая техника → Крупная техника для дома → Посудомоечные машины | E50: 639254341 | F50: 3046 | G50: =IFERROR(E50/F50,0) | H50: 296 | I50: 45 | J50: =IFERROR(E50/H50,0) | K50: =E50/'По разделам'!$B$21 | L50: =L49+K50 | M50: 00051 | N50: https://app.redstat.kz/niche/00051?event_date=2026-08-01 | O50: https://kaspi.kz/shop/c/dishwashers/
A51: 50 | B51: Мужские кроссовки и кеды | C51: Обувь | D51: Обувь → Мужская обувь → Мужские кроссовки и кеды | E51: 630160742 | F51: 23968 | G51: =IFERROR(E51/F51,0) | H51: 12808 | I51: 446 | J51: =IFERROR(E51/H51,0) | K51: =E51/'По разделам'!$B$21 | L51: =L50+K51 | M51: 02419 | N51: https://app.redstat.kz/niche/02419?event_date=2026-08-01 | O51: https://kaspi.kz/shop/c/men%20trainers/
A52: 51 | B52: Обеденные столы | C52: Мебель | D52: Мебель → Кухня → Обеденные столы | E52: 622489680 | F52: 12652 | G52: =IFERROR(E52/F52,0) | H52: 1872 | I52: 211 | J52: =IFERROR(E52/H52,0) | K52: =E52/'По разделам'!$B$21 | L52: =L51+K52 | M52: 05340 | N52: https://app.redstat.kz/niche/05340?event_date=2026-08-01 | O52: https://kaspi.kz/shop/c/dinner%20tables/
A53: 52 | B53: Компьютерные и офисные кресла | C53: Мебель | D53: Мебель → Офис и кабинет → Компьютерные и офисные кресла | E53: 615161723 | F53: 30206 | G53: =IFERROR(E53/F53,0) | H53: 1422 | I53: 151 | J53: =IFERROR(E53/H53,0) | K53: =E53/'По разделам'!$B$21 | L53: =L52+K53 | M53: 05376 | N53: https://app.redstat.kz/niche/05376?event_date=2026-08-01 | O53: https://kaspi.kz/shop/c/desk%20chairs/
... A55: 54 | B55: Средства для умывания и очищения | C55: Красота и здоровье | D55: Красота и здоровье → Уход за лицом → Средства для умывания и очищения | E55: 594193496 | F55: 127604 | G55: =IFERROR(E55/F55,0) | H55: 3014 | I55: 693 | J55: =IFERROR(E55/H55,0) | K55: =E55/'По разделам'!$B$21 | L55: =L54+K55 | M55: 05369 | N55: https://app.redstat.kz/niche/05369?event_date=2026-08-01 | O55: https://kaspi.kz/shop/c/makeup%20removers/
A56: 55 | B56: Шторы и карнизы | C56: Товары для дома и дачи | D56: Товары для дома и дачи → Домашний текстиль → Шторы и карнизы → Шторы и карнизы | E56: 592944195 | F56: 68658 | G56: =IFERROR(E56/F56,0) | H56: 10134 | I56: 307 | J56: =IFERROR(E56/H56,0) | K56: =E56/'По разделам'!$B$21 | L56: =L55+K56 | M56: q514b672b0d8f953 | N56: https://app.redstat.kz/niche/q514b672b0d8f953?event_date=2026-08-01
A57: 56 | B57: Кухонные плиты | C57: Бытовая техника | D57: Бытовая техника → Крупная техника для дома → Кухонные плиты | E57: 591084038 | F57: 4089 | G57: =IFERROR(E57/F57,0) | H57: 630 | I57: 54 | J57: =IFERROR(E57/H57,0) | K57: =E57/'По разделам'!$B$21 | L57: =L56+K57 | M57: 00024 | N57: https://app.redstat.kz/niche/00024?event_date=2026-08-01 | O57: https://kaspi.kz/shop/c/kitcheners/
A58: 57 | B58: Варочные поверхности | C58: Бытовая техника | D58: Бытовая техника → Крупная техника для дома → Варочные поверхности | E58: 588947953 | F58: 8304 | G58: =IFERROR(E58/F58,0) | H58: 922 | I58: 99 | J58: =IFERROR(E58/H58,0) | K58: =E58/'По разделам'!$B$21 | L58: =L57+K58 | M58: 00045 | N58: https://app.redstat.kz/niche/00045?event_date=2026-08-01 | O58: https://kaspi.kz/shop/c/cooktops/
A59: 58 | B59: Садовая мебель | C59: Товары для дома и дачи | D59: Товары для дома и дачи → Дача, сад и огород → Садовая мебель → Садовая мебель | E59: 585699136 | F59: 7302 | G59: =IFERROR(E59/F59,0) | H59: 1245 | I59: 195 | J59: =IFERROR(E59/H59,0) | K59: =E59/'По разделам'!$B$21 | L59: =L58+K59 | M59: q05643297bfa24bd | N59: https://app.redstat.kz/niche/q05643297bfa24bd?event_date=2026-08-01
A60: 59 | B60: Рюкзаки | C60: Аксессуары | D60: Аксессуары → Сумки, чемоданы, кошельки → Рюкзаки | E60: 566205846 | F60: 111687 | G60: =IFERROR(E60/F60,0) | H60: 5105 | I60: 702 | J60: =IFERROR(E60/H60,0) | K60: =E60/'По разделам'!$B$21 | L60: =L59+K60 | M60: 06955 | N60: https://app.redstat.kz/niche/06955?event_date=2026-08-01 | O60: https://kaspi.kz/shop/c/backpacks/
A61: 60 | B61: Кофемашины и кофеварки | C61: Бытовая техника | D61: Бытовая техника → Мелкая техника для кухни → Кофемашины и кофеварки → Кофемашины и кофеварки | E61: 562709676 | F61: 19529 | G61: =IFERROR(E61/F61,0) | H61: 913 | I61: 239 | J61: =IFERROR(E61/H61,0) | K61: =E61/'По разделам'!$B$21 | L61: =L60+K61 | M61: q5b6dc11c1737a85 | N61: https://app.redstat.kz/niche/q5b6dc11c1737a85?event_date=2026-08-01
A62: 61 | B62: Велосипеды | C62: Спорт, туризм | D62: Спорт, туризм → Велоспорт → Велосипеды | E62: 542683303 | F62: 7623 | G62: =IFERROR(E62/F62,0) | H62: 1855 | I62: 206 | J62: =IFERROR(E62/H62,0) | K62: =E62/'По разделам'!$B$21 | L62: =L61+K62 | M62: 04876 | N62: https://app.redstat.kz/niche/04876?event_date=2026-08-01 | O62: https://kaspi.kz/shop/c/bicycles/
A63: 62 | B63: Ковры и ковровые дорожки | C63: Товары для дома и дачи | D63: Товары для дома и дачи → Домашний текстиль → Ковры и ковровые дорожки → Ковры и ковровые дорожки | E63: 540755118 | F63: 45606 | G63: =IFERROR(E63/F63,0) | H63: 8394 | I63: 409 | J63: =IFERROR(E63/H63,0) | K63: =E63/'По разделам'!$B$21 | L63: =L62+K63 | M63: q77c01931530cb87 | N63: https://app.redstat.kz/niche/q77c01931530cb87?event_date=2026-08-01
A64: 63 | B64: Двери | C64: Строительство, ремонт | D64: Строительство, ремонт → Двери, окна, лестницы → Двери → Двери | E64: 538212387 | F64: 13721 | G64: =IFERROR(E64/F64,0) | H64: 2565 | I64: 276 | J64: =IFERROR(E64/H64,0) | K64: =E64/'По разделам'!$B$21 | L64: =L63+K64 | M64: q52c7f2c1b3fe551 | N64: https://app.redstat.kz/niche/q52c7f2c1b3fe551?event_date=2026-08-01
A65: 64 | B65: Умные колонки | C65: ТВ, Аудио, Видео | D65: ТВ, Аудио, Видео → Аудиотехника → Умные колонки | E65: 528770745 | F65: 9314 | G65: =IFERROR(E65/F65,0) | H65: 209 | I65: 9 | J65: =IFERROR(E65/H65,0) | K65: =E65/'По разделам'!$B$21 | L65: =L64+K65 | M65: 00846 | N65: https://app.redstat.kz/niche/00846?event_date=2026-08-01 | O65: https://kaspi.kz/shop/c/smart%20speakers/
A66: 65 | B66: Женские кроссовки и кеды | C66: Обувь | D66: Обувь → Женская обувь → Женские кроссовки и кеды | E66: 526766652 | F66: 39773 | G66: =IFERROR(E66/F66,0) | H66: 10694 | I66: 501 | J66: =IFERROR(E66/H66,0) | K66: =E66/'По разделам'!$B$21 | L66: =L65+K66 | M66: 02406 | N66: https://app.redstat.kz/niche/02406?event_date=2026-08-01 | O66: https://kaspi.kz/shop/c/women%20trainers/
A67: 66 | B67: Шампуни для волос | C67: Красота и здоровье | D67: Красота и здоровье → Уход за волосами → Шампуни для волос | E67: 525095534 | F67: 105453 | G67: =IFERROR(E67/F67,0) | H67: 5101 | I67: 822 | J67: =IFERROR(E67/H67,0) | K67: =E67/'По разделам'!$B$21 | L67: =L66+K67 | M67: 00689 | N67: https://app.redstat.kz/niche/00689?event_date=2026-08-01 | O67: https://kaspi.kz/shop/c/hair%20shampoos/
A68: 67 | B68: Лодки, моторы и комплектующие | C68: Спорт, туризм | D68: Спорт, туризм → Товары для рыбалки → Лодки, моторы и комплектующие → Лодки, моторы и комплектующие | E68: 522854509 | F68: 6729 | G68: =IFERROR(E68/F68,0) | H68: 1365 | I68: 147 | J68: =IFERROR(E68/H68,0) | K68: =E68/'По разделам'!$B$21 | L68: =L67+K68 | M68: q0c7a7e9bdc2aa94 | N68: https://app.redstat.kz/niche/q0c7a7e9bdc2aa94?event_date=2026-08-01
A69: 68 | B69: Беговые дорожки | C69: Спорт, туризм | D69: Спорт, туризм → Тренажеры → Беговые дорожки | E69: 521837005 | F69: 12101 | G69: =IFERROR(E69/F69,0) | H69: 219 | I69: 55 | J69: =IFERROR(E69/H69,0) | K69: =E69/'По разделам'!$B$21 | L69: =L68+K69 | M69: 00767 | N69: https://app.redstat.kz/niche/00767?event_date=2026-08-01 | O69: https://kaspi.kz/shop/c/treadmills/
A70: 69 | B70: Коляски и аксессуары | C70: Детские товары | D70: Детские товары → Прогулки и поездки → Коляски и аксессуары → Коляски и аксессуары | E70: 514902010 | F70: 12835 | G70: =IFERROR(E70/F70,0) | H70: 1561 | I70: 180 | J70: =IFERROR(E70/H70,0) | K70: =E70/'По разделам'!$B$21 | L70: =L69+K70 | M70: q10841289e0c08f8 | N70: https://app.redstat.kz/niche/q10841289e0c08f8?event_date=2026-08-01
A71: 70 | B71: Фотокамеры | C71: ТВ, Аудио, Видео | D71: ТВ, Аудио, Видео → Фото- и видеокамеры → Фотокамеры | E71: 504644829 | F71: 3276 | G71: =IFERROR(E71/F71,0) | H71: 201 | I71: 17 | J71: =IFERROR(E71/H71,0) | K71: =E71/'По разделам'!$B$21 | L71: =L70+K71 | M71: 00302 | N71: https://app.redstat.kz/niche/00302?event_date=2026-08-01 | O71: https://kaspi.kz/shop/c/photo%20cameras/
A72: 71 | B72: Часы наручные | C72: Аксессуары | D72: Аксессуары → Часы → Часы наручные | E72: 503598829 | F72: 38752 | G72: =IFERROR(E72/F72,0) | H72: 3800 | I72: 331 | J72: =IFERROR(E72/H72,0) | K72: =E72/'По разделам'!$B$21 | L72: =L71+K72 | M72: 00648 | N72: https://app.redstat.kz/niche/00648?event_date=2026-08-01 | O72: https://kaspi.kz/shop/c/wrist%20watches/
A73: 72 | B73: Мониторы | C73: Компьютеры | D73: Компьютеры → Периферия → Мониторы | E73: 492164863 | F73: 4961 | G73: =IFERROR(E73/F73,0) | H73: 592 | I73: 78 | J73: =IFERROR(E73/H73,0) | K73: =E73/'По разделам'!$B$21 | L73: =L72+K73 | M73: 00011 | N73: https://app.redstat.kz/niche/00011?event_date=2026-08-01 | O73: https://kaspi.kz/shop/c/monitors/
A74: 73 | B74: Средства для стирки | C74: Товары для дома и дачи | D74: Товары для дома и дачи → Бытовая химия → Средства для стирки → Средства для стирки | E74: 487666706 | F74: 135824 | G74: =IFERROR(E74/F74,0) | H74: 4694 | I74: 635 | J74: =IFERROR(E74/H74,0) | K74: =E74/'По разделам'!$B$21 | L74: =L73+K74 | M74: q346e018d65cae8f | N74: https://app.redstat.kz/niche/q346e018d65cae8f?event_date=2026-08-01
A75: 74 | B75: Фитнес абонементы | C75: Спорт, туризм | D75: Спорт, туризм → Товары для фитнеса → Фитнес абонементы | E75: 485318555 | F75: 1682 | G75: =IFERROR(E75/F75,0) | H75: 129 | I75: 16 | J75: =IFERROR(E75/H75,0) | K75: =E75/'По разделам'!$B$21 | L75: =L74+K75 | M75: 02861 | N75: https://app.redstat.kz/niche/02861?event_date=2026-08-01 | O75: https://kaspi.kz/shop/c/gym%20membership/
A76: 75 | B76: Кемпинг | C76: Спорт, туризм | D76: Спорт, туризм → Туризм и отдых на природе → Кемпинг → Кемпинг | E76: 483039655 | F76: 41986 | G76: =IFERROR(E76/F76,0) | H76: 3801 | I76: 472 | J76: =IFERROR(E76/H76,0) | K76: =E76/'По разделам'!$B$21 | L76: =L75+K76 | M76: q8e5bea894a8d6b8 | N76: https://app.redstat.kz/niche/q8e5bea894a8d6b8?event_date=2026-08-01
A77: 76 | B77: Инвентарь для уборки | C77: Товары для дома и дачи | D77: Товары для дома и дачи → Хозяйственные товары → Инвентарь для уборки → Инвентарь для уборки | E77: 482916047 | F77: 162461 | G77: =IFERROR(E77/F77,0) | H77: 7547 | I77: 997 | J77: =IFERROR(E77/H77,0) | K77: =E77/'По разделам'!$B$21 | L77: =L76+K77 | M77: q6895d6cf9a427ba | N77: https://app.redstat.kz/niche/q6895d6cf9a427ba?event_date=2026-08-01
A78: 77 | B78: Миксеры, блендеры и измельчители | C78: Бытовая техника | D78: Бытовая техника → Мелкая техника для кухни → Миксеры, блендеры и измельчители → Миксеры, блендеры и измельчители | E78: 457302428 | F78: 28704 | G78: =IFERROR(E78/F78,0) | H78: 1723 | I78: 365 | J78: =IFERROR(E78/H78,0) | K78: =E78/'По разделам'!$B$21 | L78: =L77+K78 | M78: q6933b6dc69b8da8 | N78: https://app.redstat.kz/niche/q6933b6dc69b8da8?event_date=2026-08-01
A79: 78 | B79: Постельное белье | C79: Товары для дома и дачи | D79: Товары для дома и дачи → Домашний текстиль → Постельное белье → Постельное белье | E79: 455324727 | F79: 66726 | G79: =IFERROR(E79/F79,0) | H79: 9628 | I79: 528 | J79: =IFERROR(E79/H79,0) | K79: =E79/'По разделам'!$B$21 | L79: =L78+K79 | M79: q89f3cc7619c1897 | N79: https://app.redstat.kz/niche/q89f3cc7619c1897?event_date=2026-08-01
A80: 79 | B80: Тетради и аксессуары | C80: Канцелярские товары | D80: Канцелярские товары → Бумага и бумажная продукция → Тетради и аксессуары | E80: 452426552 | F80: 269816 | G80: =IFERROR(E80/F80,0) | H80: 5314 | I80: 137 | J80: =IFERROR(E80/H80,0) | K80: =E80/'По разделам'!$B$21 | L80: =L79+K80 | M80: 04202 | N80: https://app.redstat.kz/niche/04202?event_date=2026-08-01 | O80: https://kaspi.kz/shop/c/exercise%20notebooks/
A81: 80 | B81: Палатки, тенты и шатры | C81: Спорт, туризм | D81: Спорт, туризм → Туризм и отдых на природе → Палатки, тенты и шатры → Палатки, тенты и шатры | E81: 451205650 | F81: 12551 | G81: =IFERROR(E81/F81,0) | H81: 1454 | I81: 226 | J81: =IFERROR(E81/H81,0) | K81: =E81/'По разделам'!$B$21 | L81: =L80+K81 | M81: qc26858c139ed410 | N81: https://app.redstat.kz/niche/qc26858c139ed410?event_date=2026-08-01
A82: 81 | B82: Уход за одеждой | C82: Товары для дома и дачи | D82: Товары для дома и дачи → Хозяйственные товары → Уход за одеждой → Уход за одеждой | E82: 449835283 | F82: 94509 | G82: =IFERROR(E82/F82,0) | H82: 3393 | I82: 475 | J82: =IFERROR(E82/H82,0) | K82: =E82/'По разделам'!$B$21 | L82: =L81+K82 | M82: qb7c5faeb75566e0 | N82: https://app.redstat.kz/niche/qb7c5faeb75566e0?event_date=2026-08-01
A83: 82 | B83: Средства по уходу за волосами | C83: Красота и здоровье | D83: Красота и здоровье → Уход за волосами → Средства по уходу за волосами | E83: 441194165 | F83: 91660 | G83: =IFERROR(E83/F83,0) | H83: 2436 | I83: 512 | J83: =IFERROR(E83/H83,0) | K83: =E83/'По разделам'!$B$21 | L83: =L82+K83 | M83: 06186 | N83: https://app.redstat.kz/niche/06186?event_date=2026-08-01 | O83: https://kaspi.kz/shop/c/hair%20care%20products/
A84: 83 | B84: Женские костюмы и пиджаки | C84: Одежда | D84: Одежда → Женщинам → Женские костюмы и пиджаки → Женские костюмы и пиджаки | E84: 437314352 | F84: 32208 | G84: =IFERROR(E84/F84,0) | H84: 10310 | I84: 523 | J84: =IFERROR(E84/H84,0) | K84: =E84/'По разделам'!$B$21 | L84: =L83+K84 | M84: q33644d3dec11d5e | N84: https://app.redstat.kz/niche/q33644d3dec11d5e?event_date=2026-08-01
A85: 84 | B85: Отпариватели | C85: Бытовая техника | D85: Бытовая техника → Малая техника для дома → Отпариватели | E85: 430707710 | F85: 36496 | G85: =IFERROR(E85/F85,0) | H85: 939 | I85: 290 | J85: =IFERROR(E85/H85,0) | K85: =E85/'По разделам'!$B$21 | L85: =L84+K85 | M85: 03282 | N85: https://app.redstat.kz/niche/03282?event_date=2026-08-01 | O85: https://kaspi.kz/shop/c/garment%20steamers/
A86: 85 | B86: Сухие корма для кошек | C86: Товары для животных | D86: Товары для животных → Для кошек → Сухие корма для кошек | E86: 428724879 | F86: 43883 | G86: =IFERROR(E86/F86,0) | H86: 1904 | I86: 126 | J86: =IFERROR(E86/H86,0) | K86: =E86/'По разделам'!$B$21 | L86: =L85+K86 | M86: 04215 | N86: https://app.redstat.kz/niche/04215?event_date=2026-08-01 | O86: https://kaspi.kz/shop/c/dry%20cat%20food/
A87: 86 | B87: Детские кровати | C87: Мебель | D87: Мебель → Детская комната → Детские кровати | E87: 426384880 | F87: 3501 | G87: =IFERROR(E87/F87,0) | H87: 777 | I87: 100 | J87: =IFERROR(E87/H87,0) | K87: =E87/'По разделам'!$B$21 | L87: =L86+K87 | M87: 05606 | N87: https://app.redstat.kz/niche/05606?event_date=2026-08-01 | O87: https://kaspi.kz/shop/c/cribs/
A88: 87 | B88: Женское нижнее белье | C88: Одежда | D88: Одежда → Женщинам → Женское нижнее белье → Женское нижнее белье | E88: 415337673 | F88: 238481 | G88: =IFERROR(E88/F88,0) | H88: 13317 | I88: 800 | J88: =IFERROR(E88/H88,0) | K88: =E88/'По разделам'!$B$21 | L88: =L87+K88 | M88: qd749db7247b3885 | N88: https://app.redstat.kz/niche/qd749db7247b3885?event_date=2026-08-01
A89: 88 | B89: Люстры | C89: Товары для дома и дачи | D89: Товары для дома и дачи → Освещение → Люстры | E89: 414745485 | F89: 35924 | G89: =IFERROR(E89/F89,0) | H89: 3465 | I89: 206 | J89: =IFERROR(E89/H89,0) | K89: =E89/'По разделам'!$B$21 | L89: =L88+K89 | M89: 00695 | N89: https://app.redstat.kz/niche/00695?event_date=2026-08-01 | O89: https://kaspi.kz/shop/c/chandeliers/
A90: 89 | B90: Зеркала интерьерные | C90: Товары для дома и дачи | D90: Товары для дома и дачи → Интерьер → Зеркала интерьерные | E90: 405185648 | F90: 27976 | G90: =IFERROR(E90/F90,0) | H90: 2148 | I90: 167 | J90: =IFERROR(E90/H90,0) | K90: =E90/'По разделам'!$B$21 | L90: =L89+K90 | M90: 00777 | N90: https://app.redstat.kz/niche/00777?event_date=2026-08-01 | O90: https://kaspi.kz/shop/c/interior%20mirrors/
A91: 90 | B91: Аксессуары для ванной и туалета | C91: Товары для дома и дачи | D91: Товары для дома и дачи → Хозяйственные товары → Аксессуары для ванной и туалета → Аксессуары для ванной и туалета | E91: 392588884 | F91: 112325 | G91: =IFERROR(E91/F91,0) | H91: 8122 | I91: 810 | J91: =IFERROR(E91/H91,0) | K91: =E91/'По разделам'!$B$21 | L91: =L90+K91 | M91: q30cbfdab7bb6f67 | N91: https://app.redstat.kz/niche/q30cbfdab7bb6f67?event_date=2026-08-01
A92: 91 | B92: Кухонные принадлежности | C92: Товары для дома и дачи | D92: Товары для дома и дачи → Посуда и принадлежности → Кухонные принадлежности → Кухонные принадлежности | E92: 378419085 | F92: 126183 | G92: =IFERROR(E92/F92,0) | H92: 9023 | I92: 1074 | J92: =IFERROR(E92/H92,0) | K92: =E92/'По разделам'!$B$21 | L92: =L91+K92 | M92: q184face0052627c | N92: https://app.redstat.kz/niche/q184face0052627c?event_date=2026-08-01
A93: 92 | B93: Посуда для хранения продуктов | C93: Товары для дома и дачи | D93: Товары для дома и дачи → Посуда и принадлежности → Посуда для хранения продуктов → Посуда для хранения продуктов | E93: 376299132 | F93: 90009 | G93: =IFERROR(E93/F93,0) | H93: 6744 | I93: 731 | J93: =IFERROR(E93/H93,0) | K93: =E93/'По разделам'!$B$21 | L93: =L92+K93 | M93: q25130cb7b01a3ab | N93: https://app.redstat.kz/niche/q25130cb7b01a3ab?event_date=2026-08-01
A94: 93 | B94: Женская верхняя одежда | C94: Одежда | D94: Одежда → Женщинам → Женская верхняя одежда → Женская верхняя одежда | E94: 374485337 | F94: 18327 | G94: =IFERROR(E94/F94,0) | H94: 5934 | I94: 536 | J94: =IFERROR(E94/H94,0) | K94: =E94/'По разделам'!$B$21 | L94: =L93+K94 | M94: q65cd08456267302 | N94: https://app.redstat.kz/niche/q65cd08456267302?event_date=2026-08-01
A95: 94 | B95: Щипцы | C95: Красота и здоровье | D95: Красота и здоровье → Техника и оборудование для красоты → Щипцы | E95: 370021055 | F95: 48545 | G95: =IFERROR(E95/F95,0) | H95: 1829 | I95: 347 | J95: =IFERROR(E95/H95,0) | K95: =E95/'По разделам'!$B$21 | L95: =L94+K95 | M95: 06221 | N95: https://app.redstat.kz/niche/06221?event_date=2026-08-01 | O95: https://kaspi.kz/shop/c/hair%20crimpers/
A96: 95 | B96: Отделка стен | C96: Строительство, ремонт | D96: Строительство, ремонт → Отделочные материалы → Отделка стен → Отделка стен | E96: 369409634 | F96: 23024 | G96: =IFERROR(E96/F96,0) | H96: 3377 | I96: 217 | J96: =IFERROR(E96/H96,0) | K96: =E96/'По разделам'!$B$21 | L96: =L95+K96 | M96: q014ba8b2cdd25de | N96: https://app.redstat.kz/niche/q014ba8b2cdd25de?event_date=2026-08-01
A97: 96 | B97: Чемоданы | C97: Аксессуары | D97: Аксессуары → Сумки, чемоданы, кошельки → Чемоданы | E97: 369404639 | F97: 15871 | G97: =IFERROR(E97/F97,0) | H97: 2186 | I97: 121 | J97: =IFERROR(E97/H97,0) | K97: =E97/'По разделам'!$B$21 | L97: =L96+K97 | M97: 00640 | N97: https://app.redstat.kz/niche/00640?event_date=2026-08-01 | O97: https://kaspi.kz/shop/c/suitcases/
A98: 97 | B98: Кремы, масла и сыворотки для тела | C98: Красота и здоровье | D98: Красота и здоровье → Уход за телом → Кремы, масла и сыворотки для тела | E98: 364970850 | F98: 86837 | G98: =IFERROR(E98/F98,0) | H98: 4477 | I98: 951 | J98: =IFERROR(E98/H98,0) | K98: =E98/'По разделам'!$B$21 | L98: =L97+K98 | M98: 05007 | N98: https://app.redstat.kz/niche/05007?event_date=2026-08-01 | O98: https://kaspi.kz/shop/c/body%20creams/
A99: 98 | B99: Вытяжки | C99: Бытовая техника | D99: Бытовая техника → Крупная техника для дома → Вытяжки | E99: 361208555 | F99: 6984 | G99: =IFERROR(E99/F99,0) | H99: 787 | I99: 72 | J99: =IFERROR(E99/H99,0) | K99: =E99/'По разделам'!$B$21 | L99: =L98+K99 | M99: 00022 | N99: https://app.redstat.kz/niche/00022?event_date=2026-08-01 | O99: https://kaspi.kz/shop/c/funnels/
A100: 99 | B100: Товары для рисования | C100: Досуг, книги | D100: Досуг, книги → Хобби и творчество → Товары для рисования → Товары для рисования | E100: 347443480 | F100: 244205 | G100: =IFERROR(E100/F100,0) | H100: 10092 | I100: 584 | J100: =IFERROR(E100/H100,0) | K100: =E100/'По разделам'!$B$21 | L100: =L99+K100 | M100: qc791a6c93eb0053 | N100: https://app.redstat.kz/niche/qc791a6c93eb0053?event_date=2026-08-01
A101: 100 | B101: Электро- и бензопилы | C101: Строительство, ремонт | D101: Строительство, ремонт → Инструменты → Электро- и бензопилы → Электро- и бензопилы | E101: 346553750 | F101: 7589 | G101: =IFERROR(E101/F101,0) | H101: 1192 | I101: 238 | J101: =IFERROR(E101/H101,0) | K101: =E101/'По разделам'!$B$21 | L101: =L100+K101 | M101: qd925a45393c9d1a | N101: https://app.redstat.kz/niche/qd925a45393c9d1a?event_date=2026-08-01
A102: 101 | B102: Бассейны и аксессуары | C102: Товары для дома и дачи | D102: Товары для дома и дачи → Дача, сад и огород → Бассейны и аксессуары → Бассейны и аксессуары | E102: 343848986 | F102: 28911 | G102: =IFERROR(E102/F102,0) | H102: 2868 | I102: 258 | J102: =IFERROR(E102/H102,0) | K102: =E102/'По разделам'!$B$21 | L102: =L101+K102 | M102: qe70aaf3e431be38 | N102: https://app.redstat.kz/niche/qe70aaf3e431be38?event_date=2026-08-01
A103: 102 | B103: Унитазы, биде и аксессуары | C103: Строительство, ремонт | D103: Строительство, ремонт → Сантехника → Унитазы, биде и аксессуары → Унитазы, биде и аксессуары | E103: 339859813 | F103: 7463 | G103: =IFERROR(E103/F103,0) | H103: 954 | I103: 146 | J103: =IFERROR(E103/H103,0) | K103: =E103/'По разделам'!$B$21 | L103: =L102+K103 | M103: q298a024bbe17c25 | N103: https://app.redstat.kz/niche/q298a024bbe17c25?event_date=2026-08-01
A104: 103 | B104: Профессиональное аудио | C104: ТВ, Аудио, Видео | D104: ТВ, Аудио, Видео → Аудиотехника → Профессиональное аудио → Профессиональное аудио | E104: 339834966 | F104: 23520 | G104: =IFERROR(E104/F104,0) | H104: 896 | I104: 202 | J104: =IFERROR(E104/H104,0) | K104: =E104/'По разделам'!$B$21 | L104: =L103+K104 | M104: q16ca36d452dbb6e | N104: https://app.redstat.kz/niche/q16ca36d452dbb6e?event_date=2026-08-01
A105: 104 | B105: Очистители и увлажнители | C105: Бытовая техника | D105: Бытовая техника → Климатическая техника → Очистители и увлажнители | E105: 335843242 | F105: 13767 | G105: =IFERROR(E105/F105,0) | H105: 679 | I105: 241 | J105: =IFERROR(E105/H105,0) | K105: =E105/'По разделам'!$B$21 | L105: =L104+K105 | M105: 00050 | N105: https://app.redstat.kz/niche/00050?event_date=2026-08-01 | O105: https://kaspi.kz/shop/c/cleaners%20and%20humidifiers/
...
